snekuity/__init__.py
snekuity/api.py
snekuity/config.py
snekuity/errors.py
snekuity/logging.py
snekuity/py.typed
snekuity/settings.py
snekuity/version.py
snekuity-0.1.1.dist-info/METADATA
snekuity-0.1.1.dist-info/WHEEL
snekuity-0.1.1.dist-info/licenses/LICENSE
snekuity-0.1.1.dist-info/RECORD
