Metadata-Version: 2.4
Name: snekuity
Version: 0.1.1
Summary: Pythonic API for GnuCash
Project-URL: documentation, https://snekuity.readthedocs.io/en/stable/
Project-URL: source, https://github.com/claui/snekuity
Author-email: Claudia Pellegrino <clau@tiqua.de>
License-Expression: Apache-2.0
License-File: LICENSE
Classifier: Development Status :: 3 - Alpha
Classifier: Topic :: Utilities
Requires-Python: >=3.11
Requires-Dist: pyxdg
